headergen1/__init__.py
headergen1/description.yaml
headergen1/headergen1.json
headergen1/main.js
headergen1-1.0.3.data/data/etc/jupyter/nbconfig/notebook.d/headergen1.json
headergen1-1.0.3.data/data/share/jupyter/nbextensions/headergen1/main.js
headergen1-1.0.3.dist-info/METADATA
headergen1-1.0.3.dist-info/WHEEL
headergen1-1.0.3.dist-info/top_level.txt
headergen1-1.0.3.dist-info/RECORD
